yahoostock/__init__.py
yahoostock/extra.py
yahoostock/yahoo.py
yahoostock-1.3.1.dist-info/LICENSE
yahoostock-1.3.1.dist-info/METADATA
yahoostock-1.3.1.dist-info/WHEEL
yahoostock-1.3.1.dist-info/top_level.txt
yahoostock-1.3.1.dist-info/RECORD
