Metadata-Version: 2.1
Name: yahoostock
Version: 1.3.1
Summary: A package designed to scrape data from Yahoo Finance.
Home-page: https://github.com/rohanxs/yahoostock
Author: Rohan Singh
License: MIT
Platform: UNKNOWN
Classifier: Programming Language :: Python :: 3
Classifier: License :: OSI Approved :: MIT License
Classifier: Operating System :: OS Independent
Requires-Python: >=3.7
License-File: LICENSE
